{
	"response": {
		"version": "0.1",
		"termsofService": "http://www.wunderground.com/weather/api/d/terms.html",
		"features": {
			"hourly": 1
		}
	},
	"hourly_forecast": [{
		"FCTTIME": {
			"hour": "12",
			"hour_padded": "12",
			"min": "00",
			"min_unpadded": "0",
			"sec": "0",
			"year": "2016",
			"mon": "10",
			"mon_padded": "10",
			"mon_abbrev": "Oct",
			"mday": "1",
			"mday_padded": "01",
			"yday": "274",
			"isdst": "1",
			"epoch": "1475341200",
			"pretty": "12:00 PM CDT on October 01, 2016",
			"civil": "12:00 PM",
			"month_name": "October",
			"month_name_abbrev": "Oct",
			"weekday_name": "Saturday",
			"weekday_name_night": "Saturday Night",
			"weekday_name_abbrev": "Sat",
			"weekday_name_unlang": "Saturday",
			"weekday_name_night_unlang": "Saturday Night",
			"ampm": "PM",
			"tz": "",
			"age": "",
			"UTCDATE": ""
		},
		"temp": {
			"english": "63",
			"metric": "17"
		},
		"dewpoint": {
			"english": "58",
			"metric": "14"
		},
		"condition": "Chance of a Thunderstorm",
		"icon": "chancetstorms",
		"icon_url": "http://icons.wxug.com/i/c/k/chancetstorms.gif",
		"fctcode": "14",
		"sky": "100",
		"wspd": {
			"english": "4",
			"metric": "6"
		},
		"wdir": {
			"dir": "NE",
			"degrees": "53"
		},
		"wx": "Scattered Thunderstorms",
		"uvi": "2",
		"humidity": "86",
		"windchill": {
			"english": "-9999",
			"metric": "-9999"
		},
		"heatindex": {
			"english": "-9999",
			"metric": "-9999"
		},
		"feelslike": {
			"english": "63",
			"metric": "17"
		},
		"qpf": {
			"english": "0.0",
			"metric": "0"
		},
		"snow": {
			"english": "0.0",
			"metric": "0"
		},
		"pop": "37",
		"mslp": {
			"english": "29.99",
			"metric": "1016"
		}
	}, {
		"FCTTIME": {
			"hour": "13",
			"hour_padded": "13",
			"min": "00",
			"min_unpadded": "0",
			"sec": "0",
			"year": "2016",
			"mon": "10",
			"mon_padded": "10",
			"mon_abbrev": "Oct",
			"mday": "1",
			"mday_padded": "01",
			"yday": "274",
			"isdst": "1",
			"epoch": "1475344800",
			"pretty": "1:00 PM CDT on October 01, 2016",
			"civil": "1:00 PM",
			"month_name": "October",
			"month_name_abbrev": "Oct",
			"weekday_name": "Saturday",
			"weekday_name_night": "Saturday Night",
			"weekday_name_abbrev": "Sat",
			"weekday_name_unlang": "Saturday",
			"weekday_name_night_unlang": "Saturday Night",
			"ampm": "PM",
			"tz": "",
			"age": "",
			"UTCDATE": ""
		},
		"temp": {
			"english": "63",
			"metric": "17"
		},
		"dewpoint": {
			"english": "58",
			"metric": "14"
		},
		"condition": "Chance of a Thunderstorm",
		"icon": "chancetstorms",
		"icon_url": "http://icons.wxug.com/i/c/k/chancetstorms.gif",
		"fctcode": "14",
		"sky": "99",
		"wspd": {
			"english": "4",
			"metric": "6"
		},
		"wdir": {
			"dir": "ENE",
			"degrees": "61"
		},
		"wx": "Scattered Thunderstorms",
		"uvi": "2",
		"humidity": "84",
		"windchill": {
			"english": "-9999",
			"metric": "-9999"
		},
		"heatindex": {
			"english": "-9999",
			"metric": "-9999"
		},
		"feelslike": {
			"english": "63",
			"metric": "17"
		},
		"qpf": {
			"english": "0.04",
			"metric": "1"
		},
		"snow": {
			"english": "0.0",
			"metric": "0"
		},
		"pop": "35",
		"mslp": {
			"english": "29.98",
			"metric": "1015"
		}
	}, {
		"FCTTIME": {
			"hour": "14",
			"hour_padded": "14",
			"min": "00",
			"min_unpadded": "0",
			"sec": "0",
			"year": "2016",
			"mon": "10",
			"mon_padded": "10",
			"mon_abbrev": "Oct",
			"mday": "1",
			"mday_padded": "01",
			"yday": "274",
			"isdst": "1",
			"epoch": "1475348400",
			"pretty": "2:00 PM CDT on October 01, 2016",
			"civil": "2:00 PM",
			"month_name": "October",
			"month_name_abbrev": "Oct",
			"weekday_name": "Saturday",
			"weekday_name_night": "Saturday Night",
			"weekday_name_abbrev": "Sat",
			"weekday_name_unlang": "Saturday",
			"weekday_name_night_unlang": "Saturday Night",
			"ampm": "PM",
			"tz": "",
			"age": "",
			"UTCDATE": ""
		},
		"temp": {
			"english": "64",
			"metric": "18"
		},
		"dewpoint": {
			"english": "58",
			"metric": "14"
		},
		"condition": "Overcast",
		"icon": "cloudy",
		"icon_url": "http://icons.wxug.com/i/c/k/cloudy.gif",
		"fctcode": "4",
		"sky": "92",
		"wspd": {
			"english": "4",
			"metric": "6"
		},
		"wdir": {
			"dir": "NE",
			"degrees": "52"
		},
		"wx": "Cloudy",
		"uvi": "2",
		"humidity": "81",
		"windchill": {
			"english": "-9999",
			"metric": "-9999"
		},
		"heatindex": {
			"english": "-9999",
			"metric": "-9999"
		},
		"feelslike": {
			"english": "64",
			"metric": "18"
		},
		"qpf": {
			"english": "0.2",
			"metric": "0"
		},
		"snow": {
			"english": "0.0",
			"metric": "0"
		},
		"pop": "24",
		"mslp": {
			"english": "29.97",
			"metric": "1015"
		}
	}, {
		"FCTTIME": {
			"hour": "15",
			"hour_padded": "15",
			"min": "00",
			"min_unpadded": "0",
			"sec": "0",
			"year": "2016",
			"mon": "10",
			"mon_padded": "10",
			"mon_abbrev": "Oct",
			"mday": "1",
			"mday_padded": "01",
			"yday": "274",
			"isdst": "1",
			"epoch": "1475352000",
			"pretty": "3:00 PM CDT on October 01, 2016",
			"civil": "3:00 PM",
			"month_name": "October",
			"month_name_abbrev": "Oct",
			"weekday_name": "Saturday",
			"weekday_name_night": "Saturday Night",
			"weekday_name_abbrev": "Sat",
			"weekday_name_unlang": "Saturday",
			"weekday_name_night_unlang": "Saturday Night",
			"ampm": "PM",
			"tz": "",
			"age": "",
			"UTCDATE": ""
		},
		"temp": {
			"english": "65",
			"metric": "18"
		},
		"dewpoint": {
			"english": "57",
			"metric": "14"
		},
		"condition": "Mostly Cloudy",
		"icon": "mostlycloudy",
		"icon_url": "http://icons.wxug.com/i/c/k/mostlycloudy.gif",
		"fctcode": "3",
		"sky": "78",
		"wspd": {
			"english": "8",
			"metric": "13"
		},
		"wdir": {
			"dir": "NE",
			"degrees": "47"
		},
		"wx": "Mostly Cloudy",
		"uvi": "2",
		"humidity": "76",
		"windchill": {
			"english": "-9999",
			"metric": "-9999"
		},
		"heatindex": {
			"english": "-9999",
			"metric": "-9999"
		},
		"feelslike": {
			"english": "65",
			"metric": "18"
		},
		"qpf": {
			"english": "1.0",
			"metric": "0"
		},
		"snow": {
			"english": "0.0",
			"metric": "0"
		},
		"pop": "15",
		"mslp": {
			"english": "29.97",
			"metric": "1015"
		}
	}, {
		"FCTTIME": {
			"hour": "16",
			"hour_padded": "16",
			"min": "00",
			"min_unpadded": "0",
			"sec": "0",
			"year": "2016",
			"mon": "10",
			"mon_padded": "10",
			"mon_abbrev": "Oct",
			"mday": "1",
			"mday_padded": "01",
			"yday": "274",
			"isdst": "1",
			"epoch": "1475355600",
			"pretty": "4:00 PM CDT on October 01, 2016",
			"civil": "4:00 PM",
			"month_name": "October",
			"month_name_abbrev": "Oct",
			"weekday_name": "Saturday",
			"weekday_name_night": "Saturday Night",
			"weekday_name_abbrev": "Sat",
			"weekday_name_unlang": "Saturday",
			"weekday_name_night_unlang": "Saturday Night",
			"ampm": "PM",
			"tz": "",
			"age": "",
			"UTCDATE": ""
		},
		"temp": {
			"english": "65",
			"metric": "18"
		},
		"dewpoint": {
			"english": "57",
			"metric": "14"
		},
		"condition": "Mostly Cloudy",
		"icon": "mostlycloudy",
		"icon_url": "http://icons.wxug.com/i/c/k/mostlycloudy.gif",
		"fctcode": "3",
		"sky": "72",
		"wspd": {
			"english": "7",
			"metric": "11"
		},
		"wdir": {
			"dir": "NE",
			"degrees": "37"
		},
		"wx": "Mostly Cloudy",
		"uvi": "1",
		"humidity": "76",
		"windchill": {
			"english": "-9999",
			"metric": "-9999"
		},
		"heatindex": {
			"english": "-9999",
			"metric": "-9999"
		},
		"feelslike": {
			"english": "65",
			"metric": "18"
		},
		"qpf": {
			"english": "0.0",
			"metric": "0"
		},
		"snow": {
			"english": "0.0",
			"metric": "0"
		},
		"pop": "15",
		"mslp": {
			"english": "29.96",
			"metric": "1015"
		}
	}, {
		"FCTTIME": {
			"hour": "17",
			"hour_padded": "17",
			"min": "00",
			"min_unpadded": "0",
			"sec": "0",
			"year": "2016",
			"mon": "10",
			"mon_padded": "10",
			"mon_abbrev": "Oct",
			"mday": "1",
			"mday_padded": "01",
			"yday": "274",
			"isdst": "1",
			"epoch": "1475359200",
			"pretty": "5:00 PM CDT on October 01, 2016",
			"civil": "5:00 PM",
			"month_name": "October",
			"month_name_abbrev": "Oct",
			"weekday_name": "Saturday",
			"weekday_name_night": "Saturday Night",
			"weekday_name_abbrev": "Sat",
			"weekday_name_unlang": "Saturday",
			"weekday_name_night_unlang": "Saturday Night",
			"ampm": "PM",
			"tz": "",
			"age": "",
			"UTCDATE": ""
		},
		"temp": {
			"english": "65",
			"metric": "18"
		},
		"dewpoint": {
			"english": "56",
			"metric": "13"
		},
		"condition": "Mostly Cloudy",
		"icon": "mostlycloudy",
		"icon_url": "http://icons.wxug.com/i/c/k/mostlycloudy.gif",
		"fctcode": "3",
		"sky": "64",
		"wspd": {
			"english": "7",
			"metric": "11"
		},
		"wdir": {
			"dir": "NNE",
			"degrees": "27"
		},
		"wx": "Mostly Cloudy",
		"uvi": "0",
		"humidity": "74",
		"windchill": {
			"english": "-9999",
			"metric": "-9999"
		},
		"heatindex": {
			"english": "-9999",
			"metric": "-9999"
		},
		"feelslike": {
			"english": "65",
			"metric": "18"
		},
		"qpf": {
			"english": "0.0",
			"metric": "0"
		},
		"snow": {
			"english": "0.0",
			"metric": "0"
		},
		"pop": "15",
		"mslp": {
			"english": "29.96",
			"metric": "1015"
		}
	}, {
		"FCTTIME": {
			"hour": "18",
			"hour_padded": "18",
			"min": "00",
			"min_unpadded": "0",
			"sec": "0",
			"year": "2016",
			"mon": "10",
			"mon_padded": "10",
			"mon_abbrev": "Oct",
			"mday": "1",
			"mday_padded": "01",
			"yday": "274",
			"isdst": "1",
			"epoch": "1475362800",
			"pretty": "6:00 PM CDT on October 01, 2016",
			"civil": "6:00 PM",
			"month_name": "October",
			"month_name_abbrev": "Oct",
			"weekday_name": "Saturday",
			"weekday_name_night": "Saturday Night",
			"weekday_name_abbrev": "Sat",
			"weekday_name_unlang": "Saturday",
			"weekday_name_night_unlang": "Saturday Night",
			"ampm": "PM",
			"tz": "",
			"age": "",
			"UTCDATE": ""
		},
		"temp": {
			"english": "64",
			"metric": "18"
		},
		"dewpoint": {
			"english": "56",
			"metric": "13"
		},
		"condition": "Partly Cloudy",
		"icon": "partlycloudy",
		"icon_url": "http://icons.wxug.com/i/c/k/partlycloudy.gif",
		"fctcode": "2",
		"sky": "54",
		"wspd": {
			"english": "6",
			"metric": "10"
		},
		"wdir": {
			"dir": "NNE",
			"degrees": "25"
		},
		"wx": "Partly Cloudy",
		"uvi": "0",
		"humidity": "76",
		"windchill": {
			"english": "-9999",
			"metric": "-9999"
		},
		"heatindex": {
			"english": "-9999",
			"metric": "-9999"
		},
		"feelslike": {
			"english": "64",
			"metric": "18"
		},
		"qpf": {
			"english": "0.0",
			"metric": "0"
		},
		"snow": {
			"english": "0.0",
			"metric": "0"
		},
		"pop": "14",
		"mslp": {
			"english": "29.96",
			"metric": "1015"
		}
	}, {
		"FCTTIME": {
			"hour": "19",
			"hour_padded": "19",
			"min": "00",
			"min_unpadded": "0",
			"sec": "0",
			"year": "2016",
			"mon": "10",
			"mon_padded": "10",
			"mon_abbrev": "Oct",
			"mday": "1",
			"mday_padded": "01",
			"yday": "274",
			"isdst": "1",
			"epoch": "1475366400",
			"pretty": "7:00 PM CDT on October 01, 2016",
			"civil": "7:00 PM",
			"month_name": "October",
			"month_name_abbrev": "Oct",
			"weekday_name": "Saturday",
			"weekday_name_night": "Saturday Night",
			"weekday_name_abbrev": "Sat",
			"weekday_name_unlang": "Saturday",
			"weekday_name_night_unlang": "Saturday Night",
			"ampm": "PM",
			"tz": "",
			"age": "",
			"UTCDATE": ""
		},
		"temp": {
			"english": "63",
			"metric": "17"
		},
		"dewpoint": {
			"english": "56",
			"metric": "13"
		},
		"condition": "Partly Cloudy",
		"icon": "partlycloudy",
		"icon_url": "http://icons.wxug.com/i/c/k/nt_partlycloudy.gif",
		"fctcode": "2",
		"sky": "51",
		"wspd": {
			"english": "5",
			"metric": "8"
		},
		"wdir": {
			"dir": "NNE",
			"degrees": "23"
		},
		"wx": "Partly Cloudy",
		"uvi": "0",
		"humidity": "79",
		"windchill": {
			"english": "-9999",
			"metric": "-9999"
		},
		"heatindex": {
			"english": "-9999",
			"metric": "-9999"
		},
		"feelslike": {
			"english": "63",
			"metric": "17"
		},
		"qpf": {
			"english": "0.0",
			"metric": "0"
		},
		"snow": {
			"english": "0.0",
			"metric": "0"
		},
		"pop": "10",
		"mslp": {
			"english": "29.96",
			"metric": "1015"
		}
	}, {
		"FCTTIME": {
			"hour": "20",
			"hour_padded": "20",
			"min": "00",
			"min_unpadded": "0",
			"sec": "0",
			"year": "2016",
			"mon": "10",
			"mon_padded": "10",
			"mon_abbrev": "Oct",
			"mday": "1",
			"mday_padded": "01",
			"yday": "274",
			"isdst": "1",
			"epoch": "1475370000",
			"pretty": "8:00 PM CDT on October 01, 2016",
			"civil": "8:00 PM",
			"month_name": "October",
			"month_name_abbrev": "Oct",
			"weekday_name": "Saturday",
			"weekday_name_night": "Saturday Night",
			"weekday_name_abbrev": "Sat",
			"weekday_name_unlang": "Saturday",
			"weekday_name_night_unlang": "Saturday Night",
			"ampm": "PM",
			"tz": "",
			"age": "",
			"UTCDATE": ""
		},
		"temp": {
			"english": "62",
			"metric": "17"
		},
		"dewpoint": {
			"english": "56",
			"metric": "13"
		},
		"condition": "Mostly Cloudy",
		"icon": "mostlycloudy",
		"icon_url": "http://icons.wxug.com/i/c/k/nt_mostlycloudy.gif",
		"fctcode": "3",
		"sky": "68",
		"wspd": {
			"english": "4",
			"metric": "6"
		},
		"wdir": {
			"dir": "NNE",
			"degrees": "22"
		},
		"wx": "Mostly Cloudy",
		"uvi": "0",
		"humidity": "82",
		"windchill": {
			"english": "-9999",
			"metric": "-9999"
		},
		"heatindex": {
			"english": "-9999",
			"metric": "-9999"
		},
		"feelslike": {
			"english": "62",
			"metric": "17"
		},
		"qpf": {
			"english": "0.0",
			"metric": "0"
		},
		"snow": {
			"english": "0.0",
			"metric": "0"
		},
		"pop": "15",
		"mslp": {
			"english": "29.97",
			"metric": "1015"
		}
	}, {
		"FCTTIME": {
			"hour": "21",
			"hour_padded": "21",
			"min": "00",
			"min_unpadded": "0",
			"sec": "0",
			"year": "2016",
			"mon": "10",
			"mon_padded": "10",
			"mon_abbrev": "Oct",
			"mday": "1",
			"mday_padded": "01",
			"yday": "274",
			"isdst": "1",
			"epoch": "1475373600",
			"pretty": "9:00 PM CDT on October 01, 2016",
			"civil": "9:00 PM",
			"month_name": "October",
			"month_name_abbrev": "Oct",
			"weekday_name": "Saturday",
			"weekday_name_night": "Saturday Night",
			"weekday_name_abbrev": "Sat",
			"weekday_name_unlang": "Saturday",
			"weekday_name_night_unlang": "Saturday Night",
			"ampm": "PM",
			"tz": "",
			"age": "",
			"UTCDATE": ""
		},
		"temp": {
			"english": "61",
			"metric": "16"
		},
		"dewpoint": {
			"english": "56",
			"metric": "13"
		},
		"condition": "Mostly Cloudy",
		"icon": "mostlycloudy",
		"icon_url": "http://icons.wxug.com/i/c/k/nt_mostlycloudy.gif",
		"fctcode": "3",
		"sky": "69",
		"wspd": {
			"english": "3",
			"metric": "5"
		},
		"wdir": {
			"dir": "NNE",
			"degrees": "22"
		},
		"wx": "Mostly Cloudy",
		"uvi": "0",
		"humidity": "84",
		"windchill": {
			"english": "-9999",
			"metric": "-9999"
		},
		"heatindex": {
			"english": "-9999",
			"metric": "-9999"
		},
		"feelslike": {
			"english": "61",
			"metric": "16"
		},
		"qpf": {
			"english": "0.0",
			"metric": "0"
		},
		"snow": {
			"english": "0.0",
			"metric": "0"
		},
		"pop": "15",
		"mslp": {
			"english": "29.98",
			"metric": "1015"
		}
	}, {
		"FCTTIME": {
			"hour": "22",
			"hour_padded": "22",
			"min": "00",
			"min_unpadded": "0",
			"sec": "0",
			"year": "2016",
			"mon": "10",
			"mon_padded": "10",
			"mon_abbrev": "Oct",
			"mday": "1",
			"mday_padded": "01",
			"yday": "274",
			"isdst": "1",
			"epoch": "1475377200",
			"pretty": "10:00 PM CDT on October 01, 2016",
			"civil": "10:00 PM",
			"month_name": "October",
			"month_name_abbrev": "Oct",
			"weekday_name": "Saturday",
			"weekday_name_night": "Saturday Night",
			"weekday_name_abbrev": "Sat",
			"weekday_name_unlang": "Saturday",
			"weekday_name_night_unlang": "Saturday Night",
			"ampm": "PM",
			"tz": "",
			"age": "",
			"UTCDATE": ""
		},
		"temp": {
			"english": "61",
			"metric": "16"
		},
		"dewpoint": {
			"english": "57",
			"metric": "14"
		},
		"condition": "Mostly Cloudy",
		"icon": "mostlycloudy",
		"icon_url": "http://icons.wxug.com/i/c/k/nt_mostlycloudy.gif",
		"fctcode": "3",
		"sky": "66",
		"wspd": {
			"english": "3",
			"metric": "5"
		},
		"wdir": {
			"dir": "N",
			"degrees": "6"
		},
		"wx": "Mostly Cloudy",
		"uvi": "0",
		"humidity": "87",
		"windchill": {
			"english": "-9999",
			"metric": "-9999"
		},
		"heatindex": {
			"english": "-9999",
			"metric": "-9999"
		},
		"feelslike": {
			"english": "61",
			"metric": "16"
		},
		"qpf": {
			"english": "0.0",
			"metric": "0"
		},
		"snow": {
			"english": "0.0",
			"metric": "0"
		},
		"pop": "15",
		"mslp": {
			"english": "29.99",
			"metric": "1016"
		}
	}, {
		"FCTTIME": {
			"hour": "23",
			"hour_padded": "23",
			"min": "00",
			"min_unpadded": "0",
			"sec": "0",
			"year": "2016",
			"mon": "10",
			"mon_padded": "10",
			"mon_abbrev": "Oct",
			"mday": "1",
			"mday_padded": "01",
			"yday": "274",
			"isdst": "1",
			"epoch": "1475380800",
			"pretty": "11:00 PM CDT on October 01, 2016",
			"civil": "11:00 PM",
			"month_name": "October",
			"month_name_abbrev": "Oct",
			"weekday_name": "Saturday",
			"weekday_name_night": "Saturday Night",
			"weekday_name_abbrev": "Sat",
			"weekday_name_unlang": "Saturday",
			"weekday_name_night_unlang": "Saturday Night",
			"ampm": "PM",
			"tz": "",
			"age": "",
			"UTCDATE": ""
		},
		"temp": {
			"english": "60",
			"metric": "16"
		},
		"dewpoint": {
			"english": "57",
			"metric": "14"
		},
		"condition": "Mostly Cloudy",
		"icon": "mostlycloudy",
		"icon_url": "http://icons.wxug.com/i/c/k/nt_mostlycloudy.gif",
		"fctcode": "3",
		"sky": "67",
		"wspd": {
			"english": "3",
			"metric": "5"
		},
		"wdir": {
			"dir": "NNW",
			"degrees": "344"
		},
		"wx": "Mostly Cloudy",
		"uvi": "0",
		"humidity": "91",
		"windchill": {
			"english": "-9999",
			"metric": "-9999"
		},
		"heatindex": {
			"english": "-9999",
			"metric": "-9999"
		},
		"feelslike": {
			"english": "60",
			"metric": "16"
		},
		"qpf": {
			"english": "0.0",
			"metric": "0"
		},
		"snow": {
			"english": "0.0",
			"metric": "0"
		},
		"pop": "19",
		"mslp": {
			"english": "29.99",
			"metric": "1016"
		}
	}, {
		"FCTTIME": {
			"hour": "0",
			"hour_padded": "00",
			"min": "00",
			"min_unpadded": "0",
			"sec": "0",
			"year": "2016",
			"mon": "10",
			"mon_padded": "10",
			"mon_abbrev": "Oct",
			"mday": "2",
			"mday_padded": "02",
			"yday": "275",
			"isdst": "1",
			"epoch": "1475384400",
			"pretty": "12:00 AM CDT on October 02, 2016",
			"civil": "12:00 AM",
			"month_name": "October",
			"month_name_abbrev": "Oct",
			"weekday_name": "Sunday",
			"weekday_name_night": "Sunday Night",
			"weekday_name_abbrev": "Sun",
			"weekday_name_unlang": "Sunday",
			"weekday_name_night_unlang": "Sunday Night",
			"ampm": "AM",
			"tz": "",
			"age": "",
			"UTCDATE": ""
		},
		"temp": {
			"english": "60",
			"metric": "16"
		},
		"dewpoint": {
			"english": "57",
			"metric": "14"
		},
		"condition": "Mostly Cloudy",
		"icon": "mostlycloudy",
		"icon_url": "http://icons.wxug.com/i/c/k/nt_mostlycloudy.gif",
		"fctcode": "3",
		"sky": "62",
		"wspd": {
			"english": "4",
			"metric": "6"
		},
		"wdir": {
			"dir": "NNW",
			"degrees": "338"
		},
		"wx": "Mostly Cloudy",
		"uvi": "0",
		"humidity": "90",
		"windchill": {
			"english": "-9999",
			"metric": "-9999"
		},
		"heatindex": {
			"english": "-9999",
			"metric": "-9999"
		},
		"feelslike": {
			"english": "60",
			"metric": "16"
		},
		"qpf": {
			"english": "0.0",
			"metric": "0"
		},
		"snow": {
			"english": "0.0",
			"metric": "0"
		},
		"pop": "15",
		"mslp": {
			"english": "29.99",
			"metric": "1016"
		}
	}, {
		"FCTTIME": {
			"hour": "1",
			"hour_padded": "01",
			"min": "00",
			"min_unpadded": "0",
			"sec": "0",
			"year": "2016",
			"mon": "10",
			"mon_padded": "10",
			"mon_abbrev": "Oct",
			"mday": "2",
			"mday_padded": "02",
			"yday": "275",
			"isdst": "1",
			"epoch": "1475388000",
			"pretty": "1:00 AM CDT on October 02, 2016",
			"civil": "1:00 AM",
			"month_name": "October",
			"month_name_abbrev": "Oct",
			"weekday_name": "Sunday",
			"weekday_name_night": "Sunday Night",
			"weekday_name_abbrev": "Sun",
			"weekday_name_unlang": "Sunday",
			"weekday_name_night_unlang": "Sunday Night",
			"ampm": "AM",
			"tz": "",
			"age": "",
			"UTCDATE": ""
		},
		"temp": {
			"english": "60",
			"metric": "16"
		},
		"dewpoint": {
			"english": "57",
			"metric": "14"
		},
		"condition": "Mostly Cloudy",
		"icon": "mostlycloudy",
		"icon_url": "http://icons.wxug.com/i/c/k/nt_mostlycloudy.gif",
		"fctcode": "3",
		"sky": "61",
		"wspd": {
			"english": "3",
			"metric": "5"
		},
		"wdir": {
			"dir": "NNW",
			"degrees": "330"
		},
		"wx": "Mostly Cloudy",
		"uvi": "0",
		"humidity": "90",
		"windchill": {
			"english": "-9999",
			"metric": "-9999"
		},
		"heatindex": {
			"english": "-9999",
			"metric": "-9999"
		},
		"feelslike": {
			"english": "60",
			"metric": "16"
		},
		"qpf": {
			"english": "0.0",
			"metric": "0"
		},
		"snow": {
			"english": "0.0",
			"metric": "0"
		},
		"pop": "15",
		"mslp": {
			"english": "29.99",
			"metric": "1016"
		}
	}, {
		"FCTTIME": {
			"hour": "2",
			"hour_padded": "02",
			"min": "00",
			"min_unpadded": "0",
			"sec": "0",
			"year": "2016",
			"mon": "10",
			"mon_padded": "10",
			"mon_abbrev": "Oct",
			"mday": "2",
			"mday_padded": "02",
			"yday": "275",
			"isdst": "1",
			"epoch": "1475391600",
			"pretty": "2:00 AM CDT on October 02, 2016",
			"civil": "2:00 AM",
			"month_name": "October",
			"month_name_abbrev": "Oct",
			"weekday_name": "Sunday",
			"weekday_name_night": "Sunday Night",
			"weekday_name_abbrev": "Sun",
			"weekday_name_unlang": "Sunday",
			"weekday_name_night_unlang": "Sunday Night",
			"ampm": "AM",
			"tz": "",
			"age": "",
			"UTCDATE": ""
		},
		"temp": {
			"english": "59",
			"metric": "15"
		},
		"dewpoint": {
			"english": "57",
			"metric": "14"
		},
		"condition": "Mostly Cloudy",
		"icon": "mostlycloudy",
		"icon_url": "http://icons.wxug.com/i/c/k/nt_mostlycloudy.gif",
		"fctcode": "3",
		"sky": "60",
		"wspd": {
			"english": "4",
			"metric": "6"
		},
		"wdir": {
			"dir": "NW",
			"degrees": "316"
		},
		"wx": "Mostly Cloudy",
		"uvi": "0",
		"humidity": "92",
		"windchill": {
			"english": "-9999",
			"metric": "-9999"
		},
		"heatindex": {
			"english": "-9999",
			"metric": "-9999"
		},
		"feelslike": {
			"english": "59",
			"metric": "15"
		},
		"qpf": {
			"english": "0.0",
			"metric": "0"
		},
		"snow": {
			"english": "0.0",
			"metric": "0"
		},
		"pop": "15",
		"mslp": {
			"english": "29.99",
			"metric": "1016"
		}
	}, {
		"FCTTIME": {
			"hour": "3",
			"hour_padded": "03",
			"min": "00",
			"min_unpadded": "0",
			"sec": "0",
			"year": "2016",
			"mon": "10",
			"mon_padded": "10",
			"mon_abbrev": "Oct",
			"mday": "2",
			"mday_padded": "02",
			"yday": "275",
			"isdst": "1",
			"epoch": "1475395200",
			"pretty": "3:00 AM CDT on October 02, 2016",
			"civil": "3:00 AM",
			"month_name": "October",
			"month_name_abbrev": "Oct",
			"weekday_name": "Sunday",
			"weekday_name_night": "Sunday Night",
			"weekday_name_abbrev": "Sun",
			"weekday_name_unlang": "Sunday",
			"weekday_name_night_unlang": "Sunday Night",
			"ampm": "AM",
			"tz": "",
			"age": "",
			"UTCDATE": ""
		},
		"temp": {
			"english": "59",
			"metric": "15"
		},
		"dewpoint": {
			"english": "57",
			"metric": "14"
		},
		"condition": "Mostly Cloudy",
		"icon": "mostlycloudy",
		"icon_url": "http://icons.wxug.com/i/c/k/nt_mostlycloudy.gif",
		"fctcode": "3",
		"sky": "66",
		"wspd": {
			"english": "3",
			"metric": "5"
		},
		"wdir": {
			"dir": "NW",
			"degrees": "311"
		},
		"wx": "Mostly Cloudy",
		"uvi": "0",
		"humidity": "93",
		"windchill": {
			"english": "-9999",
			"metric": "-9999"
		},
		"heatindex": {
			"english": "-9999",
			"metric": "-9999"
		},
		"feelslike": {
			"english": "59",
			"metric": "15"
		},
		"qpf": {
			"english": "0.0",
			"metric": "0"
		},
		"snow": {
			"english": "0.0",
			"metric": "0"
		},
		"pop": "19",
		"mslp": {
			"english": "29.99",
			"metric": "1016"
		}
	}, {
		"FCTTIME": {
			"hour": "4",
			"hour_padded": "04",
			"min": "00",
			"min_unpadded": "0",
			"sec": "0",
			"year": "2016",
			"mon": "10",
			"mon_padded": "10",
			"mon_abbrev": "Oct",
			"mday": "2",
			"mday_padded": "02",
			"yday": "275",
			"isdst": "1",
			"epoch": "1475398800",
			"pretty": "4:00 AM CDT on October 02, 2016",
			"civil": "4:00 AM",
			"month_name": "October",
			"month_name_abbrev": "Oct",
			"weekday_name": "Sunday",
			"weekday_name_night": "Sunday Night",
			"weekday_name_abbrev": "Sun",
			"weekday_name_unlang": "Sunday",
			"weekday_name_night_unlang": "Sunday Night",
			"ampm": "AM",
			"tz": "",
			"age": "",
			"UTCDATE": ""
		},
		"temp": {
			"english": "59",
			"metric": "15"
		},
		"dewpoint": {
			"english": "57",
			"metric": "14"
		},
		"condition": "Partly Cloudy",
		"icon": "partlycloudy",
		"icon_url": "http://icons.wxug.com/i/c/k/nt_partlycloudy.gif",
		"fctcode": "2",
		"sky": "47",
		"wspd": {
			"english": "4",
			"metric": "6"
		},
		"wdir": {
			"dir": "NW",
			"degrees": "315"
		},
		"wx": "Partly Cloudy",
		"uvi": "0",
		"humidity": "93",
		"windchill": {
			"english": "-9999",
			"metric": "-9999"
		},
		"heatindex": {
			"english": "-9999",
			"metric": "-9999"
		},
		"feelslike": {
			"english": "59",
			"metric": "15"
		},
		"qpf": {
			"english": "0.0",
			"metric": "0"
		},
		"snow": {
			"english": "0.0",
			"metric": "0"
		},
		"pop": "21",
		"mslp": {
			"english": "29.99",
			"metric": "1016"
		}
	}, {
		"FCTTIME": {
			"hour": "5",
			"hour_padded": "05",
			"min": "00",
			"min_unpadded": "0",
			"sec": "0",
			"year": "2016",
			"mon": "10",
			"mon_padded": "10",
			"mon_abbrev": "Oct",
			"mday": "2",
			"mday_padded": "02",
			"yday": "275",
			"isdst": "1",
			"epoch": "1475402400",
			"pretty": "5:00 AM CDT on October 02, 2016",
			"civil": "5:00 AM",
			"month_name": "October",
			"month_name_abbrev": "Oct",
			"weekday_name": "Sunday",
			"weekday_name_night": "Sunday Night",
			"weekday_name_abbrev": "Sun",
			"weekday_name_unlang": "Sunday",
			"weekday_name_night_unlang": "Sunday Night",
			"ampm": "AM",
			"tz": "",
			"age": "",
			"UTCDATE": ""
		},
		"temp": {
			"english": "58",
			"metric": "14"
		},
		"dewpoint": {
			"english": "56",
			"metric": "13"
		},
		"condition": "Partly Cloudy",
		"icon": "partlycloudy",
		"icon_url": "http://icons.wxug.com/i/c/k/nt_partlycloudy.gif",
		"fctcode": "2",
		"sky": "43",
		"wspd": {
			"english": "5",
			"metric": "8"
		},
		"wdir": {
			"dir": "NW",
			"degrees": "320"
		},
		"wx": "Partly Cloudy",
		"uvi": "0",
		"humidity": "94",
		"windchill": {
			"english": "-9999",
			"metric": "-9999"
		},
		"heatindex": {
			"english": "-9999",
			"metric": "-9999"
		},
		"feelslike": {
			"english": "58",
			"metric": "14"
		},
		"qpf": {
			"english": "0.0",
			"metric": "0"
		},
		"snow": {
			"english": "0.0",
			"metric": "0"
		},
		"pop": "10",
		"mslp": {
			"english": "30.0",
			"metric": "1016"
		}
	}, {
		"FCTTIME": {
			"hour": "6",
			"hour_padded": "06",
			"min": "00",
			"min_unpadded": "0",
			"sec": "0",
			"year": "2016",
			"mon": "10",
			"mon_padded": "10",
			"mon_abbrev": "Oct",
			"mday": "2",
			"mday_padded": "02",
			"yday": "275",
			"isdst": "1",
			"epoch": "1475406000",
			"pretty": "6:00 AM CDT on October 02, 2016",
			"civil": "6:00 AM",
			"month_name": "October",
			"month_name_abbrev": "Oct",
			"weekday_name": "Sunday",
			"weekday_name_night": "Sunday Night",
			"weekday_name_abbrev": "Sun",
			"weekday_name_unlang": "Sunday",
			"weekday_name_night_unlang": "Sunday Night",
			"ampm": "AM",
			"tz": "",
			"age": "",
			"UTCDATE": ""
		},
		"temp": {
			"english": "58",
			"metric": "14"
		},
		"dewpoint": {
			"english": "56",
			"metric": "13"
		},
		"condition": "Partly Cloudy",
		"icon": "partlycloudy",
		"icon_url": "http://icons.wxug.com/i/c/k/nt_partlycloudy.gif",
		"fctcode": "2",
		"sky": "47",
		"wspd": {
			"english": "5",
			"metric": "8"
		},
		"wdir": {
			"dir": "WNW",
			"degrees": "303"
		},
		"wx": "Partly Cloudy",
		"uvi": "0",
		"humidity": "94",
		"windchill": {
			"english": "-9999",
			"metric": "-9999"
		},
		"heatindex": {
			"english": "-9999",
			"metric": "-9999"
		},
		"feelslike": {
			"english": "58",
			"metric": "14"
		},
		"qpf": {
			"english": "0.0",
			"metric": "0"
		},
		"snow": {
			"english": "0.0",
			"metric": "0"
		},
		"pop": "10",
		"mslp": {
			"english": "30.01",
			"metric": "1016"
		}
	}, {
		"FCTTIME": {
			"hour": "7",
			"hour_padded": "07",
			"min": "00",
			"min_unpadded": "0",
			"sec": "0",
			"year": "2016",
			"mon": "10",
			"mon_padded": "10",
			"mon_abbrev": "Oct",
			"mday": "2",
			"mday_padded": "02",
			"yday": "275",
			"isdst": "1",
			"epoch": "1475409600",
			"pretty": "7:00 AM CDT on October 02, 2016",
			"civil": "7:00 AM",
			"month_name": "October",
			"month_name_abbrev": "Oct",
			"weekday_name": "Sunday",
			"weekday_name_night": "Sunday Night",
			"weekday_name_abbrev": "Sun",
			"weekday_name_unlang": "Sunday",
			"weekday_name_night_unlang": "Sunday Night",
			"ampm": "AM",
			"tz": "",
			"age": "",
			"UTCDATE": ""
		},
		"temp": {
			"english": "58",
			"metric": "14"
		},
		"dewpoint": {
			"english": "56",
			"metric": "13"
		},
		"condition": "Partly Cloudy",
		"icon": "partlycloudy",
		"icon_url": "http://icons.wxug.com/i/c/k/partlycloudy.gif",
		"fctcode": "2",
		"sky": "48",
		"wspd": {
			"english": "5",
			"metric": "8"
		},
		"wdir": {
			"dir": "NW",
			"degrees": "306"
		},
		"wx": "Partly Cloudy",
		"uvi": "0",
		"humidity": "94",
		"windchill": {
			"english": "-9999",
			"metric": "-9999"
		},
		"heatindex": {
			"english": "-9999",
			"metric": "-9999"
		},
		"feelslike": {
			"english": "58",
			"metric": "14"
		},
		"qpf": {
			"english": "0.0",
			"metric": "0"
		},
		"snow": {
			"english": "0.0",
			"metric": "0"
		},
		"pop": "11",
		"mslp": {
			"english": "30.02",
			"metric": "1017"
		}
	}, {
		"FCTTIME": {
			"hour": "8",
			"hour_padded": "08",
			"min": "00",
			"min_unpadded": "0",
			"sec": "0",
			"year": "2016",
			"mon": "10",
			"mon_padded": "10",
			"mon_abbrev": "Oct",
			"mday": "2",
			"mday_padded": "02",
			"yday": "275",
			"isdst": "1",
			"epoch": "1475413200",
			"pretty": "8:00 AM CDT on October 02, 2016",
			"civil": "8:00 AM",
			"month_name": "October",
			"month_name_abbrev": "Oct",
			"weekday_name": "Sunday",
			"weekday_name_night": "Sunday Night",
			"weekday_name_abbrev": "Sun",
			"weekday_name_unlang": "Sunday",
			"weekday_name_night_unlang": "Sunday Night",
			"ampm": "AM",
			"tz": "",
			"age": "",
			"UTCDATE": ""
		},
		"temp": {
			"english": "59",
			"metric": "15"
		},
		"dewpoint": {
			"english": "56",
			"metric": "13"
		},
		"condition": "Partly Cloudy",
		"icon": "partlycloudy",
		"icon_url": "http://icons.wxug.com/i/c/k/partlycloudy.gif",
		"fctcode": "2",
		"sky": "52",
		"wspd": {
			"english": "6",
			"metric": "10"
		},
		"wdir": {
			"dir": "NW",
			"degrees": "314"
		},
		"wx": "Partly Cloudy",
		"uvi": "0",
		"humidity": "91",
		"windchill": {
			"english": "-9999",
			"metric": "-9999"
		},
		"heatindex": {
			"english": "-9999",
			"metric": "-9999"
		},
		"feelslike": {
			"english": "59",
			"metric": "15"
		},
		"qpf": {
			"english": "0.0",
			"metric": "0"
		},
		"snow": {
			"english": "0.0",
			"metric": "0"
		},
		"pop": "8",
		"mslp": {
			"english": "30.03",
			"metric": "1017"
		}
	}, {
		"FCTTIME": {
			"hour": "9",
			"hour_padded": "09",
			"min": "00",
			"min_unpadded": "0",
			"sec": "0",
			"year": "2016",
			"mon": "10",
			"mon_padded": "10",
			"mon_abbrev": "Oct",
			"mday": "2",
			"mday_padded": "02",
			"yday": "275",
			"isdst": "1",
			"epoch": "1475416800",
			"pretty": "9:00 AM CDT on October 02, 2016",
			"civil": "9:00 AM",
			"month_name": "October",
			"month_name_abbrev": "Oct",
			"weekday_name": "Sunday",
			"weekday_name_night": "Sunday Night",
			"weekday_name_abbrev": "Sun",
			"weekday_name_unlang": "Sunday",
			"weekday_name_night_unlang": "Sunday Night",
			"ampm": "AM",
			"tz": "",
			"age": "",
			"UTCDATE": ""
		},
		"temp": {
			"english": "60",
			"metric": "16"
		},
		"dewpoint": {
			"english": "56",
			"metric": "13"
		},
		"condition": "Mostly Cloudy",
		"icon": "mostlycloudy",
		"icon_url": "http://icons.wxug.com/i/c/k/mostlycloudy.gif",
		"fctcode": "3",
		"sky": "60",
		"wspd": {
			"english": "6",
			"metric": "10"
		},
		"wdir": {
			"dir": "NW",
			"degrees": "312"
		},
		"wx": "Mostly Cloudy",
		"uvi": "1",
		"humidity": "86",
		"windchill": {
			"english": "-9999",
			"metric": "-9999"
		},
		"heatindex": {
			"english": "-9999",
			"metric": "-9999"
		},
		"feelslike": {
			"english": "60",
			"metric": "16"
		},
		"qpf": {
			"english": "0.0",
			"metric": "0"
		},
		"snow": {
			"english": "0.0",
			"metric": "0"
		},
		"pop": "8",
		"mslp": {
			"english": "30.04",
			"metric": "1017"
		}
	}, {
		"FCTTIME": {
			"hour": "10",
			"hour_padded": "10",
			"min": "00",
			"min_unpadded": "0",
			"sec": "0",
			"year": "2016",
			"mon": "10",
			"mon_padded": "10",
			"mon_abbrev": "Oct",
			"mday": "2",
			"mday_padded": "02",
			"yday": "275",
			"isdst": "1",
			"epoch": "1475420400",
			"pretty": "10:00 AM CDT on October 02, 2016",
			"civil": "10:00 AM",
			"month_name": "October",
			"month_name_abbrev": "Oct",
			"weekday_name": "Sunday",
			"weekday_name_night": "Sunday Night",
			"weekday_name_abbrev": "Sun",
			"weekday_name_unlang": "Sunday",
			"weekday_name_night_unlang": "Sunday Night",
			"ampm": "AM",
			"tz": "",
			"age": "",
			"UTCDATE": ""
		},
		"temp": {
			"english": "62",
			"metric": "17"
		},
		"dewpoint": {
			"english": "57",
			"metric": "14"
		},
		"condition": "Mostly Cloudy",
		"icon": "mostlycloudy",
		"icon_url": "http://icons.wxug.com/i/c/k/mostlycloudy.gif",
		"fctcode": "3",
		"sky": "70",
		"wspd": {
			"english": "6",
			"metric": "10"
		},
		"wdir": {
			"dir": "NW",
			"degrees": "316"
		},
		"wx": "Mostly Cloudy",
		"uvi": "2",
		"humidity": "82",
		"windchill": {
			"english": "-9999",
			"metric": "-9999"
		},
		"heatindex": {
			"english": "-9999",
			"metric": "-9999"
		},
		"feelslike": {
			"english": "62",
			"metric": "17"
		},
		"qpf": {
			"english": "0.0",
			"metric": "0"
		},
		"snow": {
			"english": "0.0",
			"metric": "0"
		},
		"pop": "13",
		"mslp": {
			"english": "30.05",
			"metric": "1018"
		}
	}, {
		"FCTTIME": {
			"hour": "11",
			"hour_padded": "11",
			"min": "00",
			"min_unpadded": "0",
			"sec": "0",
			"year": "2016",
			"mon": "10",
			"mon_padded": "10",
			"mon_abbrev": "Oct",
			"mday": "2",
			"mday_padded": "02",
			"yday": "275",
			"isdst": "1",
			"epoch": "1475424000",
			"pretty": "11:00 AM CDT on October 02, 2016",
			"civil": "11:00 AM",
			"month_name": "October",
			"month_name_abbrev": "Oct",
			"weekday_name": "Sunday",
			"weekday_name_night": "Sunday Night",
			"weekday_name_abbrev": "Sun",
			"weekday_name_unlang": "Sunday",
			"weekday_name_night_unlang": "Sunday Night",
			"ampm": "AM",
			"tz": "",
			"age": "",
			"UTCDATE": ""
		},
		"temp": {
			"english": "64",
			"metric": "18"
		},
		"dewpoint": {
			"english": "56",
			"metric": "13"
		},
		"condition": "Mostly Cloudy",
		"icon": "mostlycloudy",
		"icon_url": "http://icons.wxug.com/i/c/k/mostlycloudy.gif",
		"fctcode": "3",
		"sky": "71",
		"wspd": {
			"english": "6",
			"metric": "10"
		},
		"wdir": {
			"dir": "NW",
			"degrees": "326"
		},
		"wx": "Mostly Cloudy",
		"uvi": "3",
		"humidity": "77",
		"windchill": {
			"english": "-9999",
			"metric": "-9999"
		},
		"heatindex": {
			"english": "-9999",
			"metric": "-9999"
		},
		"feelslike": {
			"english": "64",
			"metric": "18"
		},
		"qpf": {
			"english": "0.0",
			"metric": "0"
		},
		"snow": {
			"english": "0.0",
			"metric": "0"
		},
		"pop": "14",
		"mslp": {
			"english": "30.05",
			"metric": "1018"
		}
	}, {
		"FCTTIME": {
			"hour": "12",
			"hour_padded": "12",
			"min": "00",
			"min_unpadded": "0",
			"sec": "0",
			"year": "2016",
			"mon": "10",
			"mon_padded": "10",
			"mon_abbrev": "Oct",
			"mday": "2",
			"mday_padded": "02",
			"yday": "275",
			"isdst": "1",
			"epoch": "1475427600",
			"pretty": "12:00 PM CDT on October 02, 2016",
			"civil": "12:00 PM",
			"month_name": "October",
			"month_name_abbrev": "Oct",
			"weekday_name": "Sunday",
			"weekday_name_night": "Sunday Night",
			"weekday_name_abbrev": "Sun",
			"weekday_name_unlang": "Sunday",
			"weekday_name_night_unlang": "Sunday Night",
			"ampm": "PM",
			"tz": "",
			"age": "",
			"UTCDATE": ""
		},
		"temp": {
			"english": "64",
			"metric": "18"
		},
		"dewpoint": {
			"english": "56",
			"metric": "13"
		},
		"condition": "Mostly Cloudy",
		"icon": "mostlycloudy",
		"icon_url": "http://icons.wxug.com/i/c/k/mostlycloudy.gif",
		"fctcode": "3",
		"sky": "72",
		"wspd": {
			"english": "6",
			"metric": "10"
		},
		"wdir": {
			"dir": "NW",
			"degrees": "322"
		},
		"wx": "Mostly Cloudy",
		"uvi": "4",
		"humidity": "74",
		"windchill": {
			"english": "-9999",
			"metric": "-9999"
		},
		"heatindex": {
			"english": "-9999",
			"metric": "-9999"
		},
		"feelslike": {
			"english": "64",
			"metric": "18"
		},
		"qpf": {
			"english": "0.0",
			"metric": "0"
		},
		"snow": {
			"english": "0.0",
			"metric": "0"
		},
		"pop": "13",
		"mslp": {
			"english": "30.05",
			"metric": "1018"
		}
	}, {
		"FCTTIME": {
			"hour": "13",
			"hour_padded": "13",
			"min": "00",
			"min_unpadded": "0",
			"sec": "0",
			"year": "2016",
			"mon": "10",
			"mon_padded": "10",
			"mon_abbrev": "Oct",
			"mday": "2",
			"mday_padded": "02",
			"yday": "275",
			"isdst": "1",
			"epoch": "1475431200",
			"pretty": "1:00 PM CDT on October 02, 2016",
			"civil": "1:00 PM",
			"month_name": "October",
			"month_name_abbrev": "Oct",
			"weekday_name": "Sunday",
			"weekday_name_night": "Sunday Night",
			"weekday_name_abbrev": "Sun",
			"weekday_name_unlang": "Sunday",
			"weekday_name_night_unlang": "Sunday Night",
			"ampm": "PM",
			"tz": "",
			"age": "",
			"UTCDATE": ""
		},
		"temp": {
			"english": "65",
			"metric": "18"
		},
		"dewpoint": {
			"english": "55",
			"metric": "13"
		},
		"condition": "Mostly Cloudy",
		"icon": "mostlycloudy",
		"icon_url": "http://icons.wxug.com/i/c/k/mostlycloudy.gif",
		"fctcode": "3",
		"sky": "74",
		"wspd": {
			"english": "6",
			"metric": "10"
		},
		"wdir": {
			"dir": "NNW",
			"degrees": "332"
		},
		"wx": "Mostly Cloudy",
		"uvi": "4",
		"humidity": "71",
		"windchill": {
			"english": "-9999",
			"metric": "-9999"
		},
		"heatindex": {
			"english": "-9999",
			"metric": "-9999"
		},
		"feelslike": {
			"english": "65",
			"metric": "18"
		},
		"qpf": {
			"english": "0.0",
			"metric": "0"
		},
		"snow": {
			"english": "0.0",
			"metric": "0"
		},
		"pop": "22",
		"mslp": {
			"english": "30.05",
			"metric": "1018"
		}
	}, {
		"FCTTIME": {
			"hour": "14",
			"hour_padded": "14",
			"min": "00",
			"min_unpadded": "0",
			"sec": "0",
			"year": "2016",
			"mon": "10",
			"mon_padded": "10",
			"mon_abbrev": "Oct",
			"mday": "2",
			"mday_padded": "02",
			"yday": "275",
			"isdst": "1",
			"epoch": "1475434800",
			"pretty": "2:00 PM CDT on October 02, 2016",
			"civil": "2:00 PM",
			"month_name": "October",
			"month_name_abbrev": "Oct",
			"weekday_name": "Sunday",
			"weekday_name_night": "Sunday Night",
			"weekday_name_abbrev": "Sun",
			"weekday_name_unlang": "Sunday",
			"weekday_name_night_unlang": "Sunday Night",
			"ampm": "PM",
			"tz": "",
			"age": "",
			"UTCDATE": ""
		},
		"temp": {
			"english": "66",
			"metric": "19"
		},
		"dewpoint": {
			"english": "55",
			"metric": "13"
		},
		"condition": "Mostly Cloudy",
		"icon": "mostlycloudy",
		"icon_url": "http://icons.wxug.com/i/c/k/mostlycloudy.gif",
		"fctcode": "3",
		"sky": "76",
		"wspd": {
			"english": "5",
			"metric": "8"
		},
		"wdir": {
			"dir": "NNW",
			"degrees": "332"
		},
		"wx": "Mostly Cloudy",
		"uvi": "3",
		"humidity": "68",
		"windchill": {
			"english": "-9999",
			"metric": "-9999"
		},
		"heatindex": {
			"english": "-9999",
			"metric": "-9999"
		},
		"feelslike": {
			"english": "66",
			"metric": "19"
		},
		"qpf": {
			"english": "0.0",
			"metric": "0"
		},
		"snow": {
			"english": "0.0",
			"metric": "0"
		},
		"pop": "20",
		"mslp": {
			"english": "30.04",
			"metric": "1017"
		}
	}, {
		"FCTTIME": {
			"hour": "15",
			"hour_padded": "15",
			"min": "00",
			"min_unpadded": "0",
			"sec": "0",
			"year": "2016",
			"mon": "10",
			"mon_padded": "10",
			"mon_abbrev": "Oct",
			"mday": "2",
			"mday_padded": "02",
			"yday": "275",
			"isdst": "1",
			"epoch": "1475438400",
			"pretty": "3:00 PM CDT on October 02, 2016",
			"civil": "3:00 PM",
			"month_name": "October",
			"month_name_abbrev": "Oct",
			"weekday_name": "Sunday",
			"weekday_name_night": "Sunday Night",
			"weekday_name_abbrev": "Sun",
			"weekday_name_unlang": "Sunday",
			"weekday_name_night_unlang": "Sunday Night",
			"ampm": "PM",
			"tz": "",
			"age": "",
			"UTCDATE": ""
		},
		"temp": {
			"english": "66",
			"metric": "19"
		},
		"dewpoint": {
			"english": "55",
			"metric": "13"
		},
		"condition": "Overcast",
		"icon": "cloudy",
		"icon_url": "http://icons.wxug.com/i/c/k/cloudy.gif",
		"fctcode": "4",
		"sky": "85",
		"wspd": {
			"english": "6",
			"metric": "10"
		},
		"wdir": {
			"dir": "NNW",
			"degrees": "347"
		},
		"wx": "Cloudy",
		"uvi": "2",
		"humidity": "68",
		"windchill": {
			"english": "-9999",
			"metric": "-9999"
		},
		"heatindex": {
			"english": "-9999",
			"metric": "-9999"
		},
		"feelslike": {
			"english": "66",
			"metric": "19"
		},
		"qpf": {
			"english": "0.0",
			"metric": "0"
		},
		"snow": {
			"english": "0.0",
			"metric": "0"
		},
		"pop": "24",
		"mslp": {
			"english": "30.03",
			"metric": "1017"
		}
	}, {
		"FCTTIME": {
			"hour": "16",
			"hour_padded": "16",
			"min": "00",
			"min_unpadded": "0",
			"sec": "0",
			"year": "2016",
			"mon": "10",
			"mon_padded": "10",
			"mon_abbrev": "Oct",
			"mday": "2",
			"mday_padded": "02",
			"yday": "275",
			"isdst": "1",
			"epoch": "1475442000",
			"pretty": "4:00 PM CDT on October 02, 2016",
			"civil": "4:00 PM",
			"month_name": "October",
			"month_name_abbrev": "Oct",
			"weekday_name": "Sunday",
			"weekday_name_night": "Sunday Night",
			"weekday_name_abbrev": "Sun",
			"weekday_name_unlang": "Sunday",
			"weekday_name_night_unlang": "Sunday Night",
			"ampm": "PM",
			"tz": "",
			"age": "",
			"UTCDATE": ""
		},
		"temp": {
			"english": "66",
			"metric": "19"
		},
		"dewpoint": {
			"english": "55",
			"metric": "13"
		},
		"condition": "Overcast",
		"icon": "cloudy",
		"icon_url": "http://icons.wxug.com/i/c/k/cloudy.gif",
		"fctcode": "4",
		"sky": "89",
		"wspd": {
			"english": "7",
			"metric": "11"
		},
		"wdir": {
			"dir": "N",
			"degrees": "3"
		},
		"wx": "Cloudy",
		"uvi": "1",
		"humidity": "70",
		"windchill": {
			"english": "-9999",
			"metric": "-9999"
		},
		"heatindex": {
			"english": "-9999",
			"metric": "-9999"
		},
		"feelslike": {
			"english": "66",
			"metric": "19"
		},
		"qpf": {
			"english": "0.0",
			"metric": "0"
		},
		"snow": {
			"english": "0.0",
			"metric": "0"
		},
		"pop": "21",
		"mslp": {
			"english": "30.03",
			"metric": "1017"
		}
	}, {
		"FCTTIME": {
			"hour": "17",
			"hour_padded": "17",
			"min": "00",
			"min_unpadded": "0",
			"sec": "0",
			"year": "2016",
			"mon": "10",
			"mon_padded": "10",
			"mon_abbrev": "Oct",
			"mday": "2",
			"mday_padded": "02",
			"yday": "275",
			"isdst": "1",
			"epoch": "1475445600",
			"pretty": "5:00 PM CDT on October 02, 2016",
			"civil": "5:00 PM",
			"month_name": "October",
			"month_name_abbrev": "Oct",
			"weekday_name": "Sunday",
			"weekday_name_night": "Sunday Night",
			"weekday_name_abbrev": "Sun",
			"weekday_name_unlang": "Sunday",
			"weekday_name_night_unlang": "Sunday Night",
			"ampm": "PM",
			"tz": "",
			"age": "",
			"UTCDATE": ""
		},
		"temp": {
			"english": "65",
			"metric": "18"
		},
		"dewpoint": {
			"english": "55",
			"metric": "13"
		},
		"condition": "Overcast",
		"icon": "cloudy",
		"icon_url": "http://icons.wxug.com/i/c/k/cloudy.gif",
		"fctcode": "4",
		"sky": "91",
		"wspd": {
			"english": "6",
			"metric": "10"
		},
		"wdir": {
			"dir": "N",
			"degrees": "3"
		},
		"wx": "Cloudy",
		"uvi": "0",
		"humidity": "71",
		"windchill": {
			"english": "-9999",
			"metric": "-9999"
		},
		"heatindex": {
			"english": "-9999",
			"metric": "-9999"
		},
		"feelslike": {
			"english": "65",
			"metric": "18"
		},
		"qpf": {
			"english": "0.0",
			"metric": "0"
		},
		"snow": {
			"english": "0.0",
			"metric": "0"
		},
		"pop": "24",
		"mslp": {
			"english": "30.04",
			"metric": "1017"
		}
	}, {
		"FCTTIME": {
			"hour": "18",
			"hour_padded": "18",
			"min": "00",
			"min_unpadded": "0",
			"sec": "0",
			"year": "2016",
			"mon": "10",
			"mon_padded": "10",
			"mon_abbrev": "Oct",
			"mday": "2",
			"mday_padded": "02",
			"yday": "275",
			"isdst": "1",
			"epoch": "1475449200",
			"pretty": "6:00 PM CDT on October 02, 2016",
			"civil": "6:00 PM",
			"month_name": "October",
			"month_name_abbrev": "Oct",
			"weekday_name": "Sunday",
			"weekday_name_night": "Sunday Night",
			"weekday_name_abbrev": "Sun",
			"weekday_name_unlang": "Sunday",
			"weekday_name_night_unlang": "Sunday Night",
			"ampm": "PM",
			"tz": "",
			"age": "",
			"UTCDATE": ""
		},
		"temp": {
			"english": "64",
			"metric": "18"
		},
		"dewpoint": {
			"english": "55",
			"metric": "13"
		},
		"condition": "Overcast",
		"icon": "cloudy",
		"icon_url": "http://icons.wxug.com/i/c/k/cloudy.gif",
		"fctcode": "4",
		"sky": "90",
		"wspd": {
			"english": "6",
			"metric": "10"
		},
		"wdir": {
			"dir": "N",
			"degrees": "8"
		},
		"wx": "Cloudy",
		"uvi": "0",
		"humidity": "73",
		"windchill": {
			"english": "-9999",
			"metric": "-9999"
		},
		"heatindex": {
			"english": "-9999",
			"metric": "-9999"
		},
		"feelslike": {
			"english": "64",
			"metric": "18"
		},
		"qpf": {
			"english": "0.0",
			"metric": "0"
		},
		"snow": {
			"english": "0.0",
			"metric": "0"
		},
		"pop": "24",
		"mslp": {
			"english": "30.04",
			"metric": "1017"
		}
	}, {
		"FCTTIME": {
			"hour": "19",
			"hour_padded": "19",
			"min": "00",
			"min_unpadded": "0",
			"sec": "0",
			"year": "2016",
			"mon": "10",
			"mon_padded": "10",
			"mon_abbrev": "Oct",
			"mday": "2",
			"mday_padded": "02",
			"yday": "275",
			"isdst": "1",
			"epoch": "1475452800",
			"pretty": "7:00 PM CDT on October 02, 2016",
			"civil": "7:00 PM",
			"month_name": "October",
			"month_name_abbrev": "Oct",
			"weekday_name": "Sunday",
			"weekday_name_night": "Sunday Night",
			"weekday_name_abbrev": "Sun",
			"weekday_name_unlang": "Sunday",
			"weekday_name_night_unlang": "Sunday Night",
			"ampm": "PM",
			"tz": "",
			"age": "",
			"UTCDATE": ""
		},
		"temp": {
			"english": "63",
			"metric": "17"
		},
		"dewpoint": {
			"english": "56",
			"metric": "13"
		},
		"condition": "Mostly Cloudy",
		"icon": "mostlycloudy",
		"icon_url": "http://icons.wxug.com/i/c/k/nt_mostlycloudy.gif",
		"fctcode": "3",
		"sky": "79",
		"wspd": {
			"english": "5",
			"metric": "8"
		},
		"wdir": {
			"dir": "N",
			"degrees": "6"
		},
		"wx": "Mostly Cloudy",
		"uvi": "0",
		"humidity": "77",
		"windchill": {
			"english": "-9999",
			"metric": "-9999"
		},
		"heatindex": {
			"english": "-9999",
			"metric": "-9999"
		},
		"feelslike": {
			"english": "63",
			"metric": "17"
		},
		"qpf": {
			"english": "0.0",
			"metric": "0"
		},
		"snow": {
			"english": "0.0",
			"metric": "0"
		},
		"pop": "14",
		"mslp": {
			"english": "30.05",
			"metric": "1018"
		}
	}, {
		"FCTTIME": {
			"hour": "20",
			"hour_padded": "20",
			"min": "00",
			"min_unpadded": "0",
			"sec": "0",
			"year": "2016",
			"mon": "10",
			"mon_padded": "10",
			"mon_abbrev": "Oct",
			"mday": "2",
			"mday_padded": "02",
			"yday": "275",
			"isdst": "1",
			"epoch": "1475456400",
			"pretty": "8:00 PM CDT on October 02, 2016",
			"civil": "8:00 PM",
			"month_name": "October",
			"month_name_abbrev": "Oct",
			"weekday_name": "Sunday",
			"weekday_name_night": "Sunday Night",
			"weekday_name_abbrev": "Sun",
			"weekday_name_unlang": "Sunday",
			"weekday_name_night_unlang": "Sunday Night",
			"ampm": "PM",
			"tz": "",
			"age": "",
			"UTCDATE": ""
		},
		"temp": {
			"english": "62",
			"metric": "17"
		},
		"dewpoint": {
			"english": "56",
			"metric": "13"
		},
		"condition": "Mostly Cloudy",
		"icon": "mostlycloudy",
		"icon_url": "http://icons.wxug.com/i/c/k/nt_mostlycloudy.gif",
		"fctcode": "3",
		"sky": "76",
		"wspd": {
			"english": "4",
			"metric": "6"
		},
		"wdir": {
			"dir": "N",
			"degrees": "9"
		},
		"wx": "Mostly Cloudy",
		"uvi": "0",
		"humidity": "80",
		"windchill": {
			"english": "-9999",
			"metric": "-9999"
		},
		"heatindex": {
			"english": "-9999",
			"metric": "-9999"
		},
		"feelslike": {
			"english": "62",
			"metric": "17"
		},
		"qpf": {
			"english": "0.0",
			"metric": "0"
		},
		"snow": {
			"english": "0.0",
			"metric": "0"
		},
		"pop": "14",
		"mslp": {
			"english": "30.06",
			"metric": "1018"
		}
	}, {
		"FCTTIME": {
			"hour": "21",
			"hour_padded": "21",
			"min": "00",
			"min_unpadded": "0",
			"sec": "0",
			"year": "2016",
			"mon": "10",
			"mon_padded": "10",
			"mon_abbrev": "Oct",
			"mday": "2",
			"mday_padded": "02",
			"yday": "275",
			"isdst": "1",
			"epoch": "1475460000",
			"pretty": "9:00 PM CDT on October 02, 2016",
			"civil": "9:00 PM",
			"month_name": "October",
			"month_name_abbrev": "Oct",
			"weekday_name": "Sunday",
			"weekday_name_night": "Sunday Night",
			"weekday_name_abbrev": "Sun",
			"weekday_name_unlang": "Sunday",
			"weekday_name_night_unlang": "Sunday Night",
			"ampm": "PM",
			"tz": "",
			"age": "",
			"UTCDATE": ""
		},
		"temp": {
			"english": "62",
			"metric": "17"
		},
		"dewpoint": {
			"english": "56",
			"metric": "13"
		},
		"condition": "Mostly Cloudy",
		"icon": "mostlycloudy",
		"icon_url": "http://icons.wxug.com/i/c/k/nt_mostlycloudy.gif",
		"fctcode": "3",
		"sky": "62",
		"wspd": {
			"english": "4",
			"metric": "6"
		},
		"wdir": {
			"dir": "NNE",
			"degrees": "12"
		},
		"wx": "Mostly Cloudy",
		"uvi": "0",
		"humidity": "83",
		"windchill": {
			"english": "-9999",
			"metric": "-9999"
		},
		"heatindex": {
			"english": "-9999",
			"metric": "-9999"
		},
		"feelslike": {
			"english": "62",
			"metric": "17"
		},
		"qpf": {
			"english": "0.0",
			"metric": "0"
		},
		"snow": {
			"english": "0.0",
			"metric": "0"
		},
		"pop": "9",
		"mslp": {
			"english": "30.07",
			"metric": "1018"
		}
	}, {
		"FCTTIME": {
			"hour": "22",
			"hour_padded": "22",
			"min": "00",
			"min_unpadded": "0",
			"sec": "0",
			"year": "2016",
			"mon": "10",
			"mon_padded": "10",
			"mon_abbrev": "Oct",
			"mday": "2",
			"mday_padded": "02",
			"yday": "275",
			"isdst": "1",
			"epoch": "1475463600",
			"pretty": "10:00 PM CDT on October 02, 2016",
			"civil": "10:00 PM",
			"month_name": "October",
			"month_name_abbrev": "Oct",
			"weekday_name": "Sunday",
			"weekday_name_night": "Sunday Night",
			"weekday_name_abbrev": "Sun",
			"weekday_name_unlang": "Sunday",
			"weekday_name_night_unlang": "Sunday Night",
			"ampm": "PM",
			"tz": "",
			"age": "",
			"UTCDATE": ""
		},
		"temp": {
			"english": "61",
			"metric": "16"
		},
		"dewpoint": {
			"english": "56",
			"metric": "13"
		},
		"condition": "Partly Cloudy",
		"icon": "partlycloudy",
		"icon_url": "http://icons.wxug.com/i/c/k/nt_partlycloudy.gif",
		"fctcode": "2",
		"sky": "56",
		"wspd": {
			"english": "4",
			"metric": "6"
		},
		"wdir": {
			"dir": "N",
			"degrees": "3"
		},
		"wx": "Partly Cloudy",
		"uvi": "0",
		"humidity": "84",
		"windchill": {
			"english": "-9999",
			"metric": "-9999"
		},
		"heatindex": {
			"english": "-9999",
			"metric": "-9999"
		},
		"feelslike": {
			"english": "61",
			"metric": "16"
		},
		"qpf": {
			"english": "0.0",
			"metric": "0"
		},
		"snow": {
			"english": "0.0",
			"metric": "0"
		},
		"pop": "8",
		"mslp": {
			"english": "30.08",
			"metric": "1019"
		}
	}, {
		"FCTTIME": {
			"hour": "23",
			"hour_padded": "23",
			"min": "00",
			"min_unpadded": "0",
			"sec": "0",
			"year": "2016",
			"mon": "10",
			"mon_padded": "10",
			"mon_abbrev": "Oct",
			"mday": "2",
			"mday_padded": "02",
			"yday": "275",
			"isdst": "1",
			"epoch": "1475467200",
			"pretty": "11:00 PM CDT on October 02, 2016",
			"civil": "11:00 PM",
			"month_name": "October",
			"month_name_abbrev": "Oct",
			"weekday_name": "Sunday",
			"weekday_name_night": "Sunday Night",
			"weekday_name_abbrev": "Sun",
			"weekday_name_unlang": "Sunday",
			"weekday_name_night_unlang": "Sunday Night",
			"ampm": "PM",
			"tz": "",
			"age": "",
			"UTCDATE": ""
		},
		"temp": {
			"english": "61",
			"metric": "16"
		},
		"dewpoint": {
			"english": "56",
			"metric": "13"
		},
		"condition": "Partly Cloudy",
		"icon": "partlycloudy",
		"icon_url": "http://icons.wxug.com/i/c/k/nt_partlycloudy.gif",
		"fctcode": "2",
		"sky": "52",
		"wspd": {
			"english": "4",
			"metric": "6"
		},
		"wdir": {
			"dir": "N",
			"degrees": "353"
		},
		"wx": "Partly Cloudy",
		"uvi": "0",
		"humidity": "86",
		"windchill": {
			"english": "-9999",
			"metric": "-9999"
		},
		"heatindex": {
			"english": "-9999",
			"metric": "-9999"
		},
		"feelslike": {
			"english": "61",
			"metric": "16"
		},
		"qpf": {
			"english": "0.0",
			"metric": "0"
		},
		"snow": {
			"english": "0.0",
			"metric": "0"
		},
		"pop": "8",
		"mslp": {
			"english": "30.07",
			"metric": "1018"
		}
	}]
}
